{
  "unversionedId": "meetings",
  "id": "meetings",
  "title": "Meetings",
  "description": "The CLI allows you to perform some basic functions with meetings, including",
  "source": "@site/docs/cli/meetings.mdx",
  "sourceDirName": ".",
  "slug": "/meetings",
  "permalink": "/cli/meetings",
  "draft": false,
  "editUrl": "https://github.com/dyte-in/docs/tree/main/docs/cli/meetings.mdx",
  "tags": [],
  "version": "current",
  "lastUpdatedAt": 1539502055,
  "formattedLastUpdatedAt": "14 oct 2018",
  "sidebarPosition": 3,
  "frontMatter": {
    "sidebar_position": 3
  },
  "sidebar": "tutorialSidebar",
  "previous": {
    "title": "Getting started",
    "permalink": "/cli/getting-started"
  },
  "next": {
    "title": "Recordings",
    "permalink": "/cli/recording"
  }
}